jfuse/__init__.py
jfuse/cli.py
jfuse/coupled.py
jfuse/fuse/__init__.py
jfuse/fuse/config.py
jfuse/fuse/model.py
jfuse/fuse/physics.py
jfuse/fuse/state.py
jfuse/io/__init__.py
jfuse/io/filemanager.py
jfuse/io/netcdf.py
jfuse/optim/__init__.py
jfuse/optim/calibration.py
jfuse/routing/__init__.py
jfuse/routing/network.py
jfuse/routing/router.py
jfuse-0.1.0.dist-info/licenses/LICENSE
jfuse-0.1.0.dist-info/METADATA
jfuse-0.1.0.dist-info/WHEEL
jfuse-0.1.0.dist-info/entry_points.txt
jfuse-0.1.0.dist-info/top_level.txt
jfuse-0.1.0.dist-info/RECORD
