Metadata-Version: 2.4
Name: jfuse
Version: 0.1.0
Summary: JAX-based differentiable hydrological modeling framework implementing FUSE and routing
Author-email: Darri Eythorsson <darri.eythorsson@ucalgary.ca>
License: MIT
Project-URL: Homepage, https://github.com/CH-Earth/jfuse
Project-URL: Documentation, https://jfuse.readthedocs.io
Project-URL: Repository, https://github.com/CH-Earth/jfuse
Project-URL: Issues, https://github.com/CH-Earth/jfuse/issues
Keywords: hydrology,jax,differentiable,machine-learning,fuse,routing,water-resources
Classifier: Development Status :: 4 - Beta
Classifier: Intended Audience :: Science/Research
Classifier: License :: OSI Approved :: MIT License
Classifier: Operating System :: OS Independent
Classifier: Programming Language :: Python :: 3
Classifier: Programming Language :: Python :: 3.9
Classifier: Programming Language :: Python :: 3.10
Classifier: Programming Language :: Python :: 3.11
Classifier: Programming Language :: Python :: 3.12
Classifier: Topic :: Scientific/Engineering :: Hydrology
Classifier: Topic :: Scientific/Engineering :: Artificial Intelligence
Requires-Python: >=3.9
License-File: LICENSE
Requires-Dist: jax>=0.4.20
Requires-Dist: jaxlib>=0.4.20
Requires-Dist: numpy>=1.24.0
Requires-Dist: xarray>=2023.1.0
Requires-Dist: netcdf4>=1.6.0
Requires-Dist: pandas>=2.0.0
Requires-Dist: optax>=0.1.7
Requires-Dist: equinox>=0.11.0
Requires-Dist: typing-extensions>=4.5.0
Provides-Extra: dev
Requires-Dist: pytest>=7.0; extra == "dev"
Requires-Dist: pytest-cov>=4.0; extra == "dev"
Requires-Dist: black>=23.0; extra == "dev"
Requires-Dist: isort>=5.12; extra == "dev"
Requires-Dist: mypy>=1.0; extra == "dev"
Requires-Dist: ruff>=0.1.0; extra == "dev"
Provides-Extra: viz
Requires-Dist: matplotlib>=3.7.0; extra == "viz"
Requires-Dist: geopandas>=0.14.0; extra == "viz"
Requires-Dist: contextily>=1.4.0; extra == "viz"
Provides-Extra: gpu
Requires-Dist: jax[cuda12_pip]>=0.4.20; extra == "gpu"
Provides-Extra: all
Requires-Dist: jfuse[dev,gpu,viz]; extra == "all"
Dynamic: license-file
